urduhack_lite/__init__.py
urduhack_lite/stop_words.py
urduhack_lite/urdu_characters.py
urduhack_lite/normalization/__init__.py
urduhack_lite/normalization/character.py
urduhack_lite/normalization/regexes.py
urduhack_lite/tokenization/__init__.py
urduhack_lite/tokenization/eos.py
urduhack_lite/tokenization/tokenizer.py
urduhack_lite-0.2.0.dist-info/METADATA
urduhack_lite-0.2.0.dist-info/WHEEL
urduhack_lite-0.2.0.dist-info/RECORD
