Metadata-Version: 2.3
Name: urduhack-lite
Version: 0.2.0
Summary: Natural Language Processing (NLP) library for Urdu language.
Author-email: Ikram Ali <mrikram1989@gmail.com>, hamzashezad <9590983+hamzashezad@users.noreply.github.com>
Requires-Python: >=3.8
